abstract_react/__init__.py
abstract_react/analyze_utils/__init__.py
abstract_react/analyze_utils/imports.py
abstract_react/analyze_utils/main.py
abstract_react/analyze_utils/src/__init__.py
abstract_react/analyze_utils/src/graph_utils.py
abstract_react/analyze_utils/src/importGraphWorker.py
abstract_react/analyze_utils/src/invert_utils.py
abstract_react/analyze_utils/src/utils.py
abstract_react/build_utils/__init__.py
abstract_react/build_utils/imports.py
abstract_react/build_utils/main.py
abstract_react/build_utils/src/__init__.py
abstract_react/build_utils/src/error_utils.py
abstract_react/build_utils/src/file_utils.py
abstract_react/build_utils/src/fixit.py
abstract_react/build_utils/src/fixit_utils.py
abstract_react/build_utils/src/path_utils.py
abstract_react/build_utils/src/parse_utils/__init__.py
abstract_react/build_utils/src/parse_utils/project_parsr.py
abstract_react/clean_imports/__init__.py
abstract_react/clean_imports/main.py
abstract_react/clean_imports/src/__init__.py
abstract_react/clean_imports/src/functions/__init__.py
abstract_react/clean_imports/src/functions/consolidateUtils.py
abstract_react/clean_imports/src/functions/diffUtils.py
abstract_react/clean_imports/src/functions/fileUtils.py
abstract_react/clean_imports/src/functions/importUtils.py
abstract_react/clean_imports/src/functions/pathUtils.py
abstract_react/clean_imports/src/functions/processingUtils.py
abstract_react/clean_imports/src/functions/readWriteUtils.py
abstract_react/clean_imports/src/functions/tsConfigHandling.py
abstract_react/clean_imports/src/imports/__init__.py
abstract_react/clean_imports/src/imports/constants.py
abstract_react/clean_imports/src/imports/init_imports.py
abstract_react/clean_imports/src/imports/schemas.py
abstract_react/import_resolver/__init__.py
abstract_react/import_resolver/main.py
abstract_react/import_resolver/imports/__init__.py
abstract_react/import_resolver/imports/constants.py
abstract_react/import_resolver/imports/init_imports.py
abstract_react-0.0.0.74.dist-info/METADATA
abstract_react-0.0.0.74.dist-info/WHEEL
abstract_react-0.0.0.74.dist-info/top_level.txt
abstract_react-0.0.0.74.dist-info/RECORD
